log_decorator/__init__.py
log_decorator/core.py
bs_log_decorator-0.1.0.dist-info/METADATA
bs_log_decorator-0.1.0.dist-info/WHEEL
bs_log_decorator-0.1.0.dist-info/RECORD
