Metadata-Version: 2.4
Name: bs-log-decorator
Version: 0.1.0
Summary: Um decorador de logging flexível para Python
Project-URL: Homepage, https://github.com/bruno-sardou/log-decorator
Project-URL: Bug Tracker, https://github.com/bruno-sardou/log-decorator/issues
Author-email: Bruno Sardou <bruno.sardou@outlook.com>
Classifier: License :: OSI Approved :: MIT License
Classifier: Operating System :: OS Independent
Classifier: Programming Language :: Python :: 3
Requires-Python: >=3.7
Requires-Dist: loguru>=0.5.0
